{
  "balance": 39648.25651799912,
  "positions": [
    {
      "symbol": "EPICUSDT",
      "amount": 897.0099667774087,
      "entryPrice": 3.01
    },
    {
      "symbol": "XUSDUSDT",
      "amount": 2700,
      "entryPrice": 1,
      "highPnlPercent": 0.009999999999998899
    },
    {
      "symbol": "ALPINEUSDT",
      "amount": 10802.361393448471,
      "entryPrice": 2.090537353591615,
      "highPnlPercent": 0.8157389635316653,
      "takeProfitPercent": 1.5,
      "highPrice": 2.098
    },
    {
      "symbol": "IOUSDT",
      "amount": 16718.388625592415,
      "entryPrice": 0.633,
      "highPrice": 0.633
    },
    {
      "symbol": "BERAUSDT",
      "amount": 7728.375034619476,
      "entryPrice": 2.2246565316749716,
      "highPrice": 2.232
    },
    {
      "symbol": "AAVEUSDT",
      "amount": 23.585257073536233,
      "entryPrice": 280.27,
      "highPrice": 280.27,
      "highPnlPercent": 0.12131159239306091
    }
  ]
}